dr_service/__init__.py
dr_service-0.1.0.dist-info/METADATA
dr_service-0.1.0.dist-info/WHEEL
dr_service-0.1.0.dist-info/RECORD
