Metadata-Version: 2.1
Name: dr-service
Version: 0.1.0
Summary: 
Author: Your Name
Author-email: you@example.com
Requires-Python: >=3.10,<4.0
Classifier: Programming Language :: Python :: 3
Classifier: Programming Language :: Python :: 3.10
Classifier: Programming Language :: Python :: 3.11
Requires-Dist: gradio (>=3.41.2,<4.0.0)
Requires-Dist: langchain (>=0.0.273,<0.0.274)
Requires-Dist: openai (>=0.27.9,<0.28.0)
Requires-Dist: pypdf (>=3.15.3,<4.0.0)
Requires-Dist: tiktoken (>=0.4.0,<0.5.0)
